{
  "faqs": [
    {
      "question": "Как сделать заказ?",
      "answer": "Вы можете позвонить нам по указанным номерам или же заполнить форму заказа и мы перезвоним вам для уточнения деталей.",
      "open": false
    },
    {
      "question": "Как я могу оплатить заказ?",
      "answer": "Мы работаем по предоплате и с наложенным платежем. Если вы из Харькова, возможен самовывоз.",
      "open": false
    },
    {
      "question": "Как осуществляется доставка?",
      "answer": "Инструмент отправляем Новой почтой или Укрпочтой.",
      "open": false
    },
    {
      "question": "Могу ли я вернуть товар?",
      "answer": "Если товар не удовлетворил вас по какому-то критерию, то вы можете вернуть его в течении 14 дней.",
      "open": false
    }

  ]
}